usg_utils/__init__.py
usg_utils/core.py
usg_utils-0.1.1.dist-info/licenses/LICENSE
usg_utils-0.1.1.dist-info/METADATA
usg_utils-0.1.1.dist-info/WHEEL
usg_utils-0.1.1.dist-info/top_level.txt
usg_utils-0.1.1.dist-info/RECORD
